Multiplier/rtl/multiplier.sv
module multiplier #(
    parameter WIDTH = 8
)(
    input  logic [WIDTH-1:0] a,
    input  logic [WIDTH-1:0] b,
    output logic [(2*WIDTH)-1:0] product
);

always_comb begin
    product = a * b;
end

endmodule

Multiplier/tb/multiplier_tb.sv
`timescale 1ns/1ps

module multiplier_tb;

parameter WIDTH = 8;

logic [WIDTH-1:0] a;
logic [WIDTH-1:0] b;
logic [(2*WIDTH)-1:0] product;

// Khai báo DUT
multiplier #(
    .WIDTH(WIDTH)
) dut (
    .a(a),
    .b(b),
    .product(product)
);

initial begin
    // Khai báo biến xử lý file
    int file_in, file_out;
    int status;
    
    // Cấu hình lưu file sóng vào thư mục sim/
    $dumpfile("sim/waveform.vcd");
    $dumpvars(0, multiplier_tb);

    // Mở file input (để đọc) và file output (để ghi)
    file_in = $fopen("sim/input.txt", "r");
    file_out = $fopen("sim/output_sv.txt", "w");

    if (file_in == 0 || file_out == 0) begin
        $display("[!] LOI: Khong the mo file du lieu."); // Đã bỏ dấu
        $finish;
    end

    $display("-----------------------------------");
    $display("     MO PHONG VOI FILE DU LIEU"); // Đã bỏ dấu
    $display("-----------------------------------");

    // Đọc từng dòng cho đến khi hết file input.txt
    while (!$feof(file_in)) begin
        // Quét lấy 2 giá trị a và b từ mỗi dòng
        status = $fscanf(file_in, "%d %d\n", a, b);
        
        #1; // Đợi mạch tổ hợp (multiplier) tính toán

        // Ghi kết quả product vừa tính được ra file output_sv.txt
        $fdisplay(file_out, "%d", product);
    end

    // Đóng file để giải phóng bộ nhớ
    $fclose(file_in);
    $fclose(file_out);

    $display("     MO PHONG HOAN TAT"); // Đã bỏ dấu
    $display("-----------------------------------");
    $finish;
end

endmodule

Multiplier/sim/waveform.vcd
$date
	Sun Jul 05 15:41:42 2026
$end
$version
	ModelSim Version 2020.1
$end
$timescale
	1ps
$end

$scope module multiplier_tb $end
$var parameter 32 ! WIDTH $end
$var reg 8 " a [7:0] $end
$var reg 8 # b [7:0] $end
$var reg 16 $ product [15:0] $end

$scope module dut $end
$var parameter 32 % WIDTH $end
$var wire 1 & a [7] $end
$var wire 1 ' a [6] $end
$var wire 1 ( a [5] $end
$var wire 1 ) a [4] $end
$var wire 1 * a [3] $end
$var wire 1 + a [2] $end
$var wire 1 , a [1] $end
$var wire 1 - a [0] $end
$var wire 1 . b [7] $end
$var wire 1 / b [6] $end
$var wire 1 0 b [5] $end
$var wire 1 1 b [4] $end
$var wire 1 2 b [3] $end
$var wire 1 3 b [2] $end
$var wire 1 4 b [1] $end
$var wire 1 5 b [0] $end
$var reg 16 6 product [15:0] $end
$upscope $end
$upscope $end
$enddefinitions $end
#0
$dumpvars
b10111110 "
b110101 #
b10011101010110 $
b10011101010110 6
b1000 !
b1000 %
0-
1,
1+
1*
1)
1(
0'
1&
15
04
13
02
11
10
0/
0.
$end
#1000
b11111111 "
b10010110 #
05
14
00
1.
1-
1'
b1001010101101010 6
b1001010101101010 $
#2000
b100110 "
b1101101 #
15
04
12
01
10
1/
0.
0-
0*
0)
0'
0&
b1000000101110 6
b1000000101110 $
#3000
b10000100 "
b11100010 #
05
14
03
02
1.
0,
0(
1&
b111010010001000 6
b111010010001000 $
#4000
b10100011 "
b11000110 #
13
00
1-
1,
0+
1(
b111111000010010 6
b111111000010010 $
#5000
b11011111 "
b100110 #
10
0/
0.
1+
1*
1)
0(
1'
b10000100011010 6
b10000100011010 $
#6000
b1010011 "
b11110100 #
04
11
1/
1.
0+
0*
0&
b100111100011100 6
b100111100011100 $
#7000
b10011110 "
b101001 #
15
03
12
01
0/
0.
0-
1+
1*
0'
1&
b1100101001110 6
b1100101001110 $
#8000
b101000 "
b11010010 #
05
14
02
11
00
1/
1.
0,
0+
0)
1(
0&
b10000011010000 6
b10000011010000 $
#9000
b1001001 "
b1101 #
15
04
13
12
01
0/
0.
1-
0(
1'
b1110110101 6
b1110110101 $
#10000
b11001000 "
b1111101 #
11
10
1/
0-
1&
b110000110101000 6
b110000110101000 $
#11000
b10100001 "
b11101110 #
05
14
01
1.
1-
0*
1(
0'
b1001010110101110 6
b1001010110101110 $
#12000
b101101 "
b1110001 #
15
04
03
02
11
0.
1+
1*
0&
b1001111011101 6
b1001111011101 $
#13000
b11111101 "
b1001110 #
05
14
13
12
01
00
1)
1'
1&
b100110100010110 6
b100110100010110 $
#14000
b10011110 "
b1101110 #
10
0-
1,
0(
0'
b100001111100100 6
b100001111100100 $
#15000
b1111010 "
b11011001 #
15
04
03
11
00
1.
0+
1(
1'
0&
b110011101101010 6
b110011101101010 $
#16000
b11100100 "
b1110000 #
05
02
10
0.
0,
1+
0*
0)
1&
b110001111000000 6
b110001111000000 $
#17000
b1000000 "
b10001101 #
15
13
12
01
00
0/
1.
0+
0(
0&
b10001101000000 6
b10001101000000 $
#18000
b10000110 "
b1000110 #
05
14
02
1/
0.
1,
1+
0'
1&
b10010010100100 6
b10010010100100 $
#19000
b10101100 "
b110 #
0/
0,
1*
1(
b10000001000 6
b10000001000 $
#20000
b100000 "
b10010110 #
11
1.
0+
0*
0&
b1001011000000 6
b1001011000000 $
#21000
b10010000 "
b1101000 #
04
03
12
01
10
1/
0.
1)
0(
1&
b11101010000000 6
b11101010000000 $
#22000
b100000 "
b1101110 #
14
13
0)
1(
0&
b110111000000 6
b110111000000 $
#23000
b111100 "
b10101110 #
0/
1.
1+
1*
1)
b10100011001000 6
b10100011001000 $
#24000
b10000010 "
b11101001 #
15
04
03
1/
1,
0+
0*
0)
0(
1&
b111011001010010 6
b111011001010010 $
#25000
b110110 "
b111000 #
05
11
0/
0.
1+
1)
1(
0&
b101111010000 6
b101111010000 $
#26000
b100000 "
b1111110 #
14
13
1/
0,
0+
0)
b111111000000 6
b111111000000 $
#27000
b10000010 "
b10000000 #
04
03
02
01
00
0/
1.
1,
0(
1&
b100000100000000 6
b100000100000000 $
#28000
b110110 "
b1010111 #
15
14
13
11
1/
0.
1+
1)
1(
0&
b1001001011010 6
b1001001011010 $
#29000
b11010001 "
b1100 #
05
04
12
01
0/
1-
0,
0+
0(
1'
1&
b100111001100 6
b100111001100 $
#30000
b1000 "
b1101110 #
14
10
1/
0-
1*
0)
0'
0&
b1101110000 6
b1101110000 $
#31000
b1110 "
b11011101 #
15
04
11
00
1.
1,
1+
b110000010110 6
b110000010110 $
#32000
b10110010 "
b1110000 #
05
03
02
10
0.
0+
0*
1)
1(
1&
b100110111100000 6
b100110111100000 $
#33000
b10100001 "
b1011101 #
15
13
12
00
1-
0,
0)
b11101001111101 6
b11101001111101 $
#34000
b1100000 "
b10000101 #
02
01
0/
1.
0-
1'
0&
b11000111100000 6
b11000111100000 $
#35000
b101100 "
b1111010 #
05
14
03
12
11
10
1/
0.
1+
1*
0'
b1010011111000 6
b1010011111000 $
#36000
b11011100 "
b1010101 #
15
04
13
02
00
1)
0(
1'
1&
b100100100001100 6
b100100100001100 $
#37000
b11010010 "
b111111 #
14
12
10
0/
1,
0+
0*
b11001110101110 6
b11001110101110 $
#38000
b1110010 "
b11111100 #
05
04
1/
1.
1(
0&
b111000000111000 6
b111000000111000 $
#39000
b10010100 "
b1110110 #
14
02
0.
0,
1+
0(
0'
1&
b100010000111000 6
b100010000111000 $
#40000
b11010010 "
b10010101 #
15
04
00
0/
1.
1,
0+
1'
b111101000111010 6
b111101000111010 $
#41000
b1000110 "
b11100010 #
05
14
03
01
10
1/
1+
0)
0&
b11110111001100 6
b11110111001100 $
#42000
b10101011 "
b1100 #
04
13
12
00
0/
0.
1-
0+
1*
1(
0'
1&
b100000000100 6
b100000000100 $
#43000
b11101100 "
b101000 #
03
10
0-
0,
1+
1'
b10010011100000 6
b10010011100000 $
#44000
b10101000 "
b11100 #
13
11
00
0+
0'
b1001001100000 6
b1001001100000 $
#45000
b100101 "
b1100001 #
15
03
02
01
10
1/
1-
1+
0*
0&
b111000000101 6
b111000000101 $
#46000
b1010 "
b11001011 #
14
12
00
1.
0-
1,
0+
1*
0(
b11111101110 6
b11111101110 $
#47000
b1111010 "
b10100011 #
02
10
0/
1)
1(
1'
b100110110101110 6
b100110110101110 $
#48000
b10101011 "
b11101110 #
05
13
12
1/
1-
0)
0'
1&
b1001111011111010 6
b1001111011111010 $
#49000
b11111110 "
b11010001 #
15
04
03
02
11
00
0-
1+
1)
1'
b1100111101011110 6
b1100111101011110 $
#50000
b11010001 "
b1100001 #
01
10
0.
1-
0,
0+
0*
0(
b100111100110001 6
b100111100110001 $
#51000
b101101 "
b110101 #
13
11
0/
1+
1*
0)
1(
0'
0&
b100101010001 6
b100101010001 $
#52000
b11110000 "
b10101010 #
05
14
03
12
01
1.
0-
0+
0*
1)
1'
1&
b1001111101100000 6
b1001111101100000 $
#53000
b1011000 "
b111001 #
15
04
11
0.
1*
0(
0&
b1001110011000 6
b1001110011000 $
#54000
b101000 "
b10100110 #
05
14
13
02
01
1.
0)
1(
0'
b1100111110000 6
b1100111110000 $
#55000
b10011001 "
b11110 #
12
11
00
0.
1-
1)
0(
1&
b1000111101110 6
b1000111101110 $
#56000
b10111101 "
b11110010 #
03
02
10
1/
1.
1+
1(
b1011001010101010 6
b1011001010101010 $
#57000
b11010 "
b11111101 #
15
04
13
12
0-
1,
0+
0(
0&
b1100110110010 6
b1100110110010 $
#58000
b1101010 "
b11110011 #
14
03
02
0)
1(
1'
b110010010011110 6
b110010010011110 $
#59000
b11000111 "
b11110 #
05
13
12
00
0/
0.
1-
1+
0*
0(
1&
b1011101010010 6
b1011101010010 $
#60000
b10011111 "
b10000010 #
03
02
01
1.
1*
1)
0'
b101000010111110 6
b101000010111110 $
#61000
b10111100 "
b1010110 #
13
11
1/
0.
0-
0,
1(
b11111100101000 6
b11111100101000 $
#62000
b101010 "
b1111100 #
04
12
10
1,
0+
0)
0&
b1010001011000 6
b1010001011000 $
#63000
b11010100 "
b1011011 #
15
14
03
00
0,
1+
0*
1)
0(
1'
1&
b100101101011100 6
b100101101011100 $
#64000
b10111 "
b11001111 #
13
01
1.
1-
1,
0'
0&
b1001010011001 6
b1001010011001 $
#65000
b10001000 "
b111100 #
05
04
11
10
0/
0.
0-
0,
0+
1*
0)
1&
b1111111100000 6
b1111111100000 $
#66000
b1111100 "
b110010 #
14
03
02
1+
1)
1(
1'
0&
b1100000111000 6
b1100000111000 $
#67000
b11101111 "
b10011 #
15
00
1-
1,
0)
1&
b1000110111101 6
b1000110111101 $
#68000
b10110111 "
b11010100 #
05
04
13
1/
1.
0*
1)
0'
b1001011110001100 6
b1001011110001100 $
#69000
b11101011 "
b11000101 #
15
01
0+
1*
0)
1'
b1011010011010111 6
b1011010011010111 $
#70000
b11110111 "
b11000111 #
14
1+
0*
1)
b1100000000000001 6
b1100000000000001 $
#71000
b10010011 "
b1111101 #
04
12
11
10
0.
0+
0(
0'
b100011111000111 6
b100011111000111 $
#72000
b11111000 "
b11010011 #
14
03
02
00
1.
0-
0,
1*
1(
1'
b1100110001101000 6
b1100110001101000 $
#73000
b11101010 "
b1010001 #
04
0.
1,
0)
b100101000001010 6
b100101000001010 $
#74000
b11010 "
b1101011 #
14
12
01
10
1)
0(
0'
0&
b101011011110 6
b101011011110 $
#75000
b10010100 "
b11010101 #
04
13
02
11
00
1.
0,
1+
0*
1&
b111101100100100 6
b111101100100100 $
#76000
b10100100 "
b10011100 #
05
12
0/
0)
1(
b110001111110000 6
b110001111110000 $
#77000
b10000010 "
b110011 #
15
14
03
02
10
0.
1,
0+
0(
b1100111100110 6
b1100111100110 $
#78000
b11010111 "
b111000 #
05
04
12
1-
1+
1)
1'
b10111100001000 6
b10111100001000 $
#79000
b10100 "
b1110 #
14
13
01
00
0-
0,
0'
0&
b100011000 6
b100011000 $
#80000
b11000 "
b10001 #
15
04
03
02
11
0+
1*
b110011000 6
b110011000 $
#81000
b10000110 "
b110110 #
05
14
13
10
1,
1+
0*
0)
1&
b1110001000100 6
b1110001000100 $
#82000
b1100001 "
b1001110 #
12
01
00
1/
1-
0,
0+
1(
1'
0&
b1110110001110 6
b1110110001110 $
#83000
b1011110 "
b10011010 #
03
11
0/
1.
0-
1,
1+
1*
1)
0(
b11100010001100 6
b11100010001100 $
#84000
b101010 "
b10100111 #
15
13
02
01
10
0+
0)
1(
0'
b1101101100110 6
b1101101100110 $
#85000
b100100 "
b10010 #
05
03
11
00
0.
0,
1+
0*
b1010001000 6
b1010001000 $
#86000
b10000101 "
b10101001 #
15
04
12
01
10
1.
1-
0(
1&
b101011111001101 6
b101011111001101 $
#87000
b11000010 "
b11000100 #
05
13
02
00
1/
0-
1,
0+
1'
b1001010010001000 6
b1001010010001000 $
#88000
b1001 "
b11101111 #
15
14
12
10
1-
0,
1*
0'
0&
b100001100111 6
b100001100111 $
#89000
b1000110 "
b1110010 #
05
03
02
11
0.
0-
1,
1+
0*
1'
b1111100101100 6
b1111100101100 $
#90000
b10110 "
b11010110 #
13
00
1.
1)
0'
b1001001100100 6
b1001001100100 $
#91000
b10000100 "
b11001000 #
04
03
12
01
0,
0)
1&
b110011100100000 6
b110011100100000 $
#92000
b10110111 "
b11010111 #
15
14
13
02
11
1-
1,
1)
1(
b1001100110110001 6
b1001100110110001 $
#93000
b10000 "
b1010110 #
05
0.
0-
0,
0+
0(
0&
b10101100000 6
b10101100000 $
#94000
b10001010 "
b10101111 #
15
12
01
10
0/
1.
1,
1*
0)
1&
b101111001010110 6
b101111001010110 $
#95000
b11101110 "
b1010100 #
05
04
02
11
00
1/
0.
1+
1(
1'
b100111000011000 6
b100111000011000 $
#96000
b11111 "
b10010110 #
14
0/
1.
1-
1)
0(
0'
0&
b1001000101010 6
b1001000101010 $
#97000
b10100011 "
b10110100 #
04
10
0+
0*
0)
1(
1&
b111001010011100 6
b111001010011100 $
#98000
b100000 "
b11111100 #
12
1/
0-
0,
0&
b1111110000000 6
b1111110000000 $
#99000
b111001 "
b10000001 #
15
03
02
01
00
0/
1-
1*
1)
b1110010111001 6
b1110010111001 $
